{ "questions":[ { "Number":"1","Question":"Qual o seu comportamento em relação aos seus investimentos?","answer":["preservar meu dinheiro sem correr riscos","ganhar mais dinheiro, assumindo riscos moderados","ganhar mais dinheiro, assumindo riscos agressivos"]},{ "Number":"2","Question":"Por quanto tempo você deseja manter os seus investimentos?","answer":["até 1 ano","de 1 a 3 anos","mais de 3 anos"]},{ "Number":"3","Question":"Quantos% desses investimentos você pode precisar em um ano?","answer":["acima de 75%","de 26% a 74%","até 25%"]},{ "Number":"4","Question":"Como você está familiarizado com os tipos de investimentos abaixo? Leve em consideração o valor aplicado nos últimos 2 anos.","answer":["Eu nunca operou","Eu tenho pouca experiência e não estou familiarizado","Opere eventualmente e conheça os riscos","Eu opero com frequência e conheço os riscos associados"], "option": ["títulos de renda fixa ou tesouraria","fundos de investimento","ações a vista","aluguel de ações, termos, opções e futuros"]}] }
